chksrv/__init__.py
chksrv/cli.py
chksrv/config.py
chksrv/exceptions.py
chksrv/runner.py
chksrv/checks/__init__.py
chksrv/checks/base.py
chksrv/checks/dns.py
chksrv/checks/http.py
chksrv/checks/ip.py
chksrv/checks/ssl.py
chksrv-0.1.0.dist-info/LICENSE
chksrv-0.1.0.dist-info/METADATA
chksrv-0.1.0.dist-info/WHEEL
chksrv-0.1.0.dist-info/entry_points.txt
chksrv-0.1.0.dist-info/top_level.txt
chksrv-0.1.0.dist-info/RECORD
