Metadata-Version: 2.1
Name: chksrv
Version: 0.1.0
Summary: A tool to probe and check the health of services
Home-page: https://git.hel.freakybytes.net/martin/chksrv
Author: Martin Peters
Author-email: 
License: UNKNOWN
Platform: UNKNOWN
Classifier: Development Status :: 3 - Alpha
Classifier: Programming Language :: Python :: 3
Classifier: Programming Language :: Python :: 3.7
Classifier: Programming Language :: Python :: 3 :: Only
Classifier: License :: OSI Approved :: GNU General Public License v3 or later (GPLv3+)
Classifier: Environment :: Console
Classifier: Intended Audience :: System Administrators
Classifier: Topic :: System :: Monitoring
Classifier: Topic :: Utilities
Requires-Dist: docopt (~=0.6)
